{"title":"WWE NXT 2016 04 06 WEBRip h264-WD [TJET]","uid":14216223,"size":678968970,"categoryP":"video","categoryS":"tv_shows","magnet":"?xt=urn:btih:0ba474bbe4c51dbba659bf4eb21b94565de1445d&amp;dn=WWE+NXT+2016+04+06+WEBRip+h264-WD+%5BTJET%5D&amp;tr=udp%3A%2F%2Ftracker.leechers-paradise.org%3A6969&amp;tr=udp%3A%2F%2Fzer0day.ch%3A1337&amp;tr=udp%3A%2F%2Fopen.demonii.com%3A1337&amp;tr=udp%3A%2F%2Ftracker.coppersurfer.tk%3A6969&amp;tr=udp%3A%2F%2Fexodus.desync.com%3A6969","seeders":2,"leechers":0,"uploader":"CenaCme","files":2,"time":1460001349,"description":"Apollo Crews and Elias Samson finally do battle, and we take a special look at the fallout from NXT TakeOver: Dallas.\r\n\r\nEvent: WWE.NXT.2016.04.06.WEBRip.h264-WD\r\nReleased: 2016.04.06\r\nSource: WWE Network\r\nResolution: 896 x 504 @ 29.970 FPS\r\nVideo: H.264 @ 1800 kbps\r\nAudio: AAC @ 96 kbps\r\nSize: 647 MB\r\nRuntime: 50mn 08sec\r\n\r\nWD: The Original\r\nHEEL\r\n\r\nUntouched/remuxed video stream from the WWE Network.\r\n\r\n\r\nThumb sheet:\r\n \nhttp://extraimago.com/image/aSMQ","torrent":{"xt":"urn:btih:0ba474bbe4c51dbba659bf4eb21b94565de1445d","amp;dn":"WWE+NXT+2016+04+06+WEBRip+h264-WD+%5BTJET%5D","amp;tr":["udp%3A%2F%2Ftracker.leechers-paradise.org%3A6969","udp%3A%2F%2Fzer0day.ch%3A1337","udp%3A%2F%2Fopen.demonii.com%3A1337","udp%3A%2F%2Ftracker.coppersurfer.tk%3A6969","udp%3A%2F%2Fexodus.desync.com%3A6969"],"infoHash":"0ba474bbe4c51dbba659bf4eb21b94565de1445d","infoHashBuffer":{"type":"Buffer","data":[11,164,116,187,228,197,29,187,166,89,191,78,178,27,148,86,93,225,68,93]},"announce":[],"urlList":[]}}