{"title":"Swing Shift  (Drama 1984)  Goldie Hawn  720p","uid":15000125,"size":1001734033,"categoryP":"video","categoryS":"movies","magnet":"?xt=urn:btih:0e3aa18c07a26f66a3990090175fd5aa4fc5c823&amp;dn=Swing+Shift++%28Drama+1984%29++Goldie+Hawn++720p&amp;tr=udp%3A%2F%2Ftracker.leechers-paradise.org%3A6969&amp;tr=udp%3A%2F%2Fzer0day.ch%3A1337&amp;tr=udp%3A%2F%2Fopen.demonii.com%3A1337&amp;tr=udp%3A%2F%2Ftracker.coppersurfer.tk%3A6969&amp;tr=udp%3A%2F%2Fexodus.desync.com%3A6969","seeders":2,"leechers":0,"uploader":"BurtonW","files":3,"time":1466370604,"description":"\nThe links below are to the IMDb and Wikipedia pages for this movie.\r\n\r\n\r\n \nhttp://www.imdb.com/title/tt0088213/?ref_=fn_al_tt_1\r\n\r\n \nhttps://en.wikipedia.org/wiki/Swing_Shift_(film)_\r\n\r\n\r\n\r\n\r\nThe quality of this print is fairly good. \r\n\r\n\r\n\r\nLanguage............: English\r\nSubtitles...........: English soft-subs &amp; SRT file\r\nDuration............: 100 mins.    @ 23.976 fps\r\nResolution..........: 1280 x 720        16:9\r\nBit rate............: 1156 Kbps\r\nAudio...............: AC3 48000Hz Stereo  160 Kbps\r\nSample..............: Included in folder  9.56 MBs\r\n\r\n\r\n\r\nStoryline:\r\n\r\n\r\n     During World War II, a navy wife (Goldie Hawn) helps the war effort by taking a job in the local aircraft factory, where she meets a man (Kurt Russell) declared unfit for military service who sweeps her off her feet. When her husband (Ed Harris) returns on a furlough, things begin to get very complicated.\r\n\r\n\r\n\r\n\r\n\r\nScreenshots:\r\n\r\n \nhttp://i.imgur.com/bG1HShR.jpg\r\n \nhttp://i.imgur.com/ou9qjKx.jpg\r\n \nhttp://i.imgur.com/Sgxtyel.jpg\r\n \nhttp://i.imgur.com/uZ04z6I.jpg\r\n \nhttp://i.imgur.com/ytK5Sxb.jpg\r\n \nhttp://i.imgur.com/6QHcdkh.jpg","torrent":{"xt":"urn:btih:0e3aa18c07a26f66a3990090175fd5aa4fc5c823","amp;dn":"Swing+Shift++%28Drama+1984%29++Goldie+Hawn++720p","amp;tr":["udp%3A%2F%2Ftracker.leechers-paradise.org%3A6969","udp%3A%2F%2Fzer0day.ch%3A1337","udp%3A%2F%2Fopen.demonii.com%3A1337","udp%3A%2F%2Ftracker.coppersurfer.tk%3A6969","udp%3A%2F%2Fexodus.desync.com%3A6969"],"infoHash":"0e3aa18c07a26f66a3990090175fd5aa4fc5c823","infoHashBuffer":{"type":"Buffer","data":[14,58,161,140,7,162,111,102,163,153,0,144,23,95,213,170,79,197,200,35]},"announce":[],"urlList":[]}}