{"title":"TRAFFIC - On the Road -1973- [320Kbps] - Drbn 125 - TRAFFIC","uid":8678174,"size":183449019,"categoryP":"audio","categoryS":"music","magnet":"?xt=urn:btih:2318470d38c15373e5d2cbd0d1a8ed4cd52c1ec9&amp;dn=TRAFFIC+-+On+the+Road+-1973-+%5B320Kbps%5D+-+Drbn+125+-+TRAFFIC&amp;tr=udp%3A%2F%2Ftracker.openbittorrent.com%3A80&amp;tr=udp%3A%2F%2Fopen.demonii.com%3A1337&amp;tr=udp%3A%2F%2Ftracker.coppersurfer.tk%3A6969&amp;tr=udp%3A%2F%2Fexodus.desync.com%3A6969","seeders":2,"leechers":1,"uploader":"Drebben","files":8,"time":1373643155,"description":"\n\nTRAFFIC\n\nON THE ROAD     1973\n\n\nCD\n- Island Masters\n- Mp3      \n- 320Kbps\n\n\n- Click  FILES  to see tracklist\n\n\n- Discover, rediscover, enjoy and seed . . .\n\n","torrent":{"xt":"urn:btih:2318470d38c15373e5d2cbd0d1a8ed4cd52c1ec9","amp;dn":"TRAFFIC+-+On+the+Road+-1973-+%5B320Kbps%5D+-+Drbn+125+-+TRAFFIC","amp;tr":["udp%3A%2F%2Ftracker.openbittorrent.com%3A80","udp%3A%2F%2Fopen.demonii.com%3A1337","udp%3A%2F%2Ftracker.coppersurfer.tk%3A6969","udp%3A%2F%2Fexodus.desync.com%3A6969"],"infoHash":"2318470d38c15373e5d2cbd0d1a8ed4cd52c1ec9","infoHashBuffer":{"type":"Buffer","data":[35,24,71,13,56,193,83,115,229,210,203,208,209,168,237,76,213,44,30,201]},"announce":[],"urlList":[]}}