{"title":"The Legend of Korra - 111-112 - Skeletons in the Closet, Endgame","uid":7380542,"size":344306022,"categoryP":"video","categoryS":"tv_shows","magnet":"?xt=urn:btih:28b0965fedd6519f622e92926444debb664333e8&amp;dn=The+Legend+of+Korra+-+111-112+-+Skeletons+in+the+Closet%2C+Endgame&amp;tr=udp%3A%2F%2Ftracker.openbittorrent.com%3A80&amp;tr=udp%3A%2F%2Fopen.demonii.com%3A1337&amp;tr=udp%3A%2F%2Ftracker.coppersurfer.tk%3A6969&amp;tr=udp%3A%2F%2Fexodus.desync.com%3A6969","seeders":2,"leechers":0,"uploader":"{C_P}","files":-1,"time":1340486864,"description":"www_cartoonpalace_info\nJoin us onChannel #cartoon_palace for more Cartoons and Anime.\n\n","torrent":{"xt":"urn:btih:28b0965fedd6519f622e92926444debb664333e8","amp;dn":"The+Legend+of+Korra+-+111-112+-+Skeletons+in+the+Closet%2C+Endgame","amp;tr":["udp%3A%2F%2Ftracker.openbittorrent.com%3A80","udp%3A%2F%2Fopen.demonii.com%3A1337","udp%3A%2F%2Ftracker.coppersurfer.tk%3A6969","udp%3A%2F%2Fexodus.desync.com%3A6969"],"infoHash":"28b0965fedd6519f622e92926444debb664333e8","infoHashBuffer":{"type":"Buffer","data":[40,176,150,95,237,214,81,159,98,46,146,146,100,68,222,187,102,67,51,232]},"announce":[],"urlList":[]}}