{"title":"Ten Thousand Saints 2015 1080p BluRay x264-ROVERS","uid":12448808,"size":8207525557,"categoryP":"video","categoryS":"hd___movies","magnet":"?xt=urn:btih:37953dd4fedb5a156605c5a4f45945a282e3bed5&amp;dn=Ten+Thousand+Saints+2015+1080p+BluRay+x264-ROVERS&amp;tr=udp%3A%2F%2Ftracker.openbittorrent.com%3A80&amp;tr=udp%3A%2F%2Fopen.demonii.com%3A1337&amp;tr=udp%3A%2F%2Ftracker.coppersurfer.tk%3A6969&amp;tr=udp%3A%2F%2Fexodus.desync.com%3A6969","seeders":2,"leechers":3,"uploader":"hotpena","files":3,"time":1442662245,"description":" SCREENS:  &lt;a href=&quot;\nhttp://icezap.com/img-55fd2bfdc62fe.html&quot; rel=&quot;nofollow&quot; target=&quot;_NEW&quot;&gt;\nhttp://icezap.com/img-55fd2bfdc62fe.html&lt;/a&gt;\n &lt;a href=&quot;\nhttp://icezap.com/img-55fd2bfdd7607.html&quot; rel=&quot;nofollow&quot; target=&quot;_NEW&quot;&gt;\nhttp://icezap.com/img-55fd2bfdd7607.html&lt;/a&gt;\n &lt;a href=&quot;\nhttp://icezap.com/img-55fd2bfde8457.html&quot; rel=&quot;nofollow&quot; target=&quot;_NEW&quot;&gt;\nhttp://icezap.com/img-55fd2bfde8457.html&lt;/a&gt;\n\n\nDOWNLOAD AND ENJOY. \n\n KEEP IT FOR LONG SEEDING TO HELP OTHERS \n\n \n Thanks to : ROVERS\n Movie Share","torrent":{"xt":"urn:btih:37953dd4fedb5a156605c5a4f45945a282e3bed5","amp;dn":"Ten+Thousand+Saints+2015+1080p+BluRay+x264-ROVERS","amp;tr":["udp%3A%2F%2Ftracker.openbittorrent.com%3A80","udp%3A%2F%2Fopen.demonii.com%3A1337","udp%3A%2F%2Ftracker.coppersurfer.tk%3A6969","udp%3A%2F%2Fexodus.desync.com%3A6969"],"infoHash":"37953dd4fedb5a156605c5a4f45945a282e3bed5","infoHashBuffer":{"type":"Buffer","data":[55,149,61,212,254,219,90,21,102,5,197,164,244,89,69,162,130,227,190,213]},"announce":[],"urlList":[]}}