{"title":"The Smiths - Strangeways, Here We Come-SiLvErDuSt#sEcTiOn8# 320 ","uid":4849969,"size":87314297,"categoryP":"audio","categoryS":"music","magnet":"?xt=urn:btih:38c1232576f7092d0174a4b261d24392ae54c3a6&amp;dn=The+Smiths+-+Strangeways%2C+Here+We+Come-SiLvErDuSt%23sEcTiOn8%23+320+&amp;tr=udp%3A%2F%2Ftracker.openbittorrent.com%3A80&amp;tr=udp%3A%2F%2Fopen.demonii.com%3A1337&amp;tr=udp%3A%2F%2Ftracker.coppersurfer.tk%3A6969&amp;tr=udp%3A%2F%2Fexodus.desync.com%3A6969","seeders":2,"leechers":0,"uploader":"dodgerblue","files":12,"time":1239831962,"description":"The Smiths - Strangeways, Here We Come-SiLvErDuSt#sEcTiOn8# 320 kbps\nTRACK LIST#\nThe Smiths - 01 - A Rush And A Push And The Land I      \nThe Smiths - 02 - I Started Something I Couldn't F      \nThe Smiths - 03 - Death Of A Disco Dancer.mp3          \nThe Smiths - 04 - Girlfriend In A Coma.mp3             \nThe Smiths - 05 - Stop Me If You Think You've Hear      \nThe Smiths - 06 - Last Night I Dreamt That Somebod     \nThe Smiths - 07 - Unhappy Birthday.mp3                  \nThe Smiths - 08 - Paint A Vulgar Picture.mp3          \nThe Smiths - 09 - Death At One's Elbow.mp3              \nThe Smiths - 10 - I Won't Share You.mp3  \n","torrent":{"xt":"urn:btih:38c1232576f7092d0174a4b261d24392ae54c3a6","amp;dn":"The+Smiths+-+Strangeways%2C+Here+We+Come-SiLvErDuSt%23sEcTiOn8%23+320+","amp;tr":["udp%3A%2F%2Ftracker.openbittorrent.com%3A80","udp%3A%2F%2Fopen.demonii.com%3A1337","udp%3A%2F%2Ftracker.coppersurfer.tk%3A6969","udp%3A%2F%2Fexodus.desync.com%3A6969"],"infoHash":"38c1232576f7092d0174a4b261d24392ae54c3a6","infoHashBuffer":{"type":"Buffer","data":[56,193,35,37,118,247,9,45,1,116,164,178,97,210,67,146,174,84,195,166]},"announce":[],"urlList":[]}}