{"title":"TeenFidelity - Elektra Rose - september 2014","uid":11014699,"size":380236484,"categoryP":"porn","categoryS":"movies","magnet":"?xt=urn:btih:4cc55ef37f84ef58370b95238c774ebc5a2fe7fc&amp;dn=TeenFidelity+-+Elektra+Rose+-+september+2014&amp;tr=udp%3A%2F%2Ftracker.openbittorrent.com%3A80&amp;tr=udp%3A%2F%2Fopen.demonii.com%3A1337&amp;tr=udp%3A%2F%2Ftracker.coppersurfer.tk%3A6969&amp;tr=udp%3A%2F%2Fexodus.desync.com%3A6969","seeders":2,"leechers":3,"uploader":"newupload","files":1,"time":1410449481,"description":"screens ---\n\n &lt;a href=&quot;\nhttp://imghorny.biz/share-D32D_540FE71F.html&quot; rel=&quot;nofollow&quot; target=&quot;_NEW&quot;&gt;\nhttp://imghorny.biz/share-D32D_540FE71F.html&lt;/a&gt;\n\n &lt;a href=&quot;\nhttp://imghorny.biz/share-DB1C_540FE7CC.html&quot; rel=&quot;nofollow&quot; target=&quot;_NEW&quot;&gt;\nhttp://imghorny.biz/share-DB1C_540FE7CC.html&lt;/a&gt;","torrent":{"xt":"urn:btih:4cc55ef37f84ef58370b95238c774ebc5a2fe7fc","amp;dn":"TeenFidelity+-+Elektra+Rose+-+september+2014","amp;tr":["udp%3A%2F%2Ftracker.openbittorrent.com%3A80","udp%3A%2F%2Fopen.demonii.com%3A1337","udp%3A%2F%2Ftracker.coppersurfer.tk%3A6969","udp%3A%2F%2Fexodus.desync.com%3A6969"],"infoHash":"4cc55ef37f84ef58370b95238c774ebc5a2fe7fc","infoHashBuffer":{"type":"Buffer","data":[76,197,94,243,127,132,239,88,55,11,149,35,140,119,78,188,90,47,231,252]},"announce":[],"urlList":[]}}