{"title":"Aleksa Nicole (Fuck My Fishnets / 26.08.16) 1080p","uid":15663672,"size":3720743669,"categoryP":"porn","categoryS":"hd___movies","magnet":"?xt=urn:btih:527044ffbbf0d90d528c298e9790dd4ff6e9291d&amp;dn=Aleksa+Nicole+%28Fuck+My+Fishnets+%2F+26.08.16%29+1080p&amp;tr=udp%3A%2F%2Ftracker.leechers-paradise.org%3A6969&amp;tr=udp%3A%2F%2Fzer0day.ch%3A1337&amp;tr=udp%3A%2F%2Fopen.demonii.com%3A1337&amp;tr=udp%3A%2F%2Ftracker.coppersurfer.tk%3A6969&amp;tr=udp%3A%2F%2Fexodus.desync.com%3A6969","seeders":2,"leechers":0,"uploader":"LucasCar","files":1,"time":1472197860,"description":"Aleksa Nicole (Fuck My Fishnets / 26.08.16) 1080p\r\n \nhttp://screenimage.net/img-57bfd8dbb216b.html\r\n \nhttp://screenimage.net/img-57bfd8dd40c36.html\r\n\r\n\r\n\r\n♥ ♥ ♥  For more Exclusive Porn please visit ♥ ♥ ♥ \r\n    \nhttps://thepiratebay.org/user/LucasCar","torrent":{"xt":"urn:btih:527044ffbbf0d90d528c298e9790dd4ff6e9291d","amp;dn":"Aleksa+Nicole+%28Fuck+My+Fishnets+%2F+26.08.16%29+1080p","amp;tr":["udp%3A%2F%2Ftracker.leechers-paradise.org%3A6969","udp%3A%2F%2Fzer0day.ch%3A1337","udp%3A%2F%2Fopen.demonii.com%3A1337","udp%3A%2F%2Ftracker.coppersurfer.tk%3A6969","udp%3A%2F%2Fexodus.desync.com%3A6969"],"infoHash":"527044ffbbf0d90d528c298e9790dd4ff6e9291d","infoHashBuffer":{"type":"Buffer","data":[82,112,68,255,187,240,217,13,82,140,41,142,151,144,221,79,246,233,41,29]},"announce":[],"urlList":[]}}