{"title":"1.erotas kai timoria S1E1.avi","uid":8735531,"size":833039920,"categoryP":"video","categoryS":"tv_shows","magnet":"?xt=urn:btih:58218787f3705e39964fbc09e9584ec5577cf284&amp;dn=1.erotas+kai+timoria+S1E1.avi&amp;tr=udp%3A%2F%2Ftracker.openbittorrent.com%3A80&amp;tr=udp%3A%2F%2Fopen.demonii.com%3A1337&amp;tr=udp%3A%2F%2Ftracker.coppersurfer.tk%3A6969&amp;tr=udp%3A%2F%2Fexodus.desync.com%3A6969","seeders":2,"leechers":0,"uploader":"katrinapapi","files":1,"time":1374679325,"description":"794MB ASK VE CEZA TURKISH SERIES TV  APOLAYSTE TO!!!!","torrent":{"xt":"urn:btih:58218787f3705e39964fbc09e9584ec5577cf284","amp;dn":"1.erotas+kai+timoria+S1E1.avi","amp;tr":["udp%3A%2F%2Ftracker.openbittorrent.com%3A80","udp%3A%2F%2Fopen.demonii.com%3A1337","udp%3A%2F%2Ftracker.coppersurfer.tk%3A6969","udp%3A%2F%2Fexodus.desync.com%3A6969"],"infoHash":"58218787f3705e39964fbc09e9584ec5577cf284","infoHashBuffer":{"type":"Buffer","data":[88,33,135,135,243,112,94,57,150,79,188,9,233,88,78,197,87,124,242,132]},"announce":[],"urlList":[]}}