{"title":"will.i.am - This Is Love (Remixes) [feat. Eva Simons] [EP - 2012","uid":7515686,"size":63286928,"categoryP":"audio","categoryS":"music","magnet":"?xt=urn:btih:749f75dfc979ca88d09e449ca104154b91aa1f20&amp;dn=will.i.am+-+This+Is+Love+%28Remixes%29+%5Bfeat.+Eva+Simons%5D+%5BEP+-+2012&amp;tr=udp%3A%2F%2Ftracker.openbittorrent.com%3A80&amp;tr=udp%3A%2F%2Fopen.demonii.com%3A1337&amp;tr=udp%3A%2F%2Ftracker.coppersurfer.tk%3A6969&amp;tr=udp%3A%2F%2Fexodus.desync.com%3A6969","seeders":2,"leechers":0,"uploader":"FatFreddy417","files":-1,"time":1344462962,"description":"Artist: will.i.am\nAlbum: This Is Love (Remixes) [feat. Eva Simons] - EP\nGenre: Dance\nBitrate: 320 kbps\nRelease date: August 07, 2012 \nSource:  &lt;a href=&quot;\nhttp://itunes.apple.com/us/album/this-is-love-remixes-feat./id548484817&quot; rel=&quot;nofollow&quot; target=&quot;_NEW&quot;&gt;\nhttp://itunes.apple.com/us/album/this-is-love-remixes-feat./id548484817&lt;/a&gt;\n\n\nT R A C K L I S T\n*****************\n01 This Is Love (Afrojack Remix)\n02 This Is Love (Sidney Samson Remix)\n03 This Is Love (Damien Le Roy Remix)\n04 This Is Love (James Egbert Remix)\n05 This Is Love (Richard Vission Solmatic Remix)\n\n\n\nPlease support the artist!\n","torrent":{"xt":"urn:btih:749f75dfc979ca88d09e449ca104154b91aa1f20","amp;dn":"will.i.am+-+This+Is+Love+%28Remixes%29+%5Bfeat.+Eva+Simons%5D+%5BEP+-+2012","amp;tr":["udp%3A%2F%2Ftracker.openbittorrent.com%3A80","udp%3A%2F%2Fopen.demonii.com%3A1337","udp%3A%2F%2Ftracker.coppersurfer.tk%3A6969","udp%3A%2F%2Fexodus.desync.com%3A6969"],"infoHash":"749f75dfc979ca88d09e449ca104154b91aa1f20","infoHashBuffer":{"type":"Buffer","data":[116,159,117,223,201,121,202,136,208,158,68,156,161,4,21,75,145,170,31,32]},"announce":[],"urlList":[]}}