{"title":"Ayami.Shunka.ABS-155.Jav.Censored.DVDRip.XviD-MotTto","uid":7687474,"size":1462394880,"categoryP":"porn","categoryS":"movies","magnet":"?xt=urn:btih:76c9612fead012a815087c0ab36c6fd2ff597ec2&amp;dn=Ayami.Shunka.ABS-155.Jav.Censored.DVDRip.XviD-MotTto&amp;tr=udp%3A%2F%2Ftracker.openbittorrent.com%3A80&amp;tr=udp%3A%2F%2Fopen.demonii.com%3A1337&amp;tr=udp%3A%2F%2Ftracker.coppersurfer.tk%3A6969&amp;tr=udp%3A%2F%2Fexodus.desync.com%3A6969","seeders":2,"leechers":1,"uploader":"digital_ripper","files":2,"time":1348999830,"description":"screens\n &lt;a href=&quot;\nhttp://mypornimage.com/adultimage/fk&quot; rel=&quot;nofollow&quot; target=&quot;_NEW&quot;&gt;\nhttp://mypornimage.com/adultimage/fk&lt;/a&gt; &lt;a href=&quot;\nhttp://mypornimage.com/adultimage/ft&quot; rel=&quot;nofollow&quot; target=&quot;_NEW&quot;&gt;\nhttp://mypornimage.com/adultimage/ft&lt;/a&gt; &lt;a href=&quot;\nhttp://mypornimage.com/adultimage/f7&quot; rel=&quot;nofollow&quot; target=&quot;_NEW&quot;&gt;\nhttp://mypornimage.com/adultimage/f7&lt;/a&gt;\n\n\n~~~~~~~~~~~~~~~~~~~~~~~~~~~~~~~~~~~~~~~~~~~~~~~~~~~~~~~~~~~~~~~~~~~~~~~~~~~~~~~\n\n(1) If you like our uploads then, Comments and Seeds\n(2) If you spot wrong images, just post a reply, new images will be available\n(3) You can request re-seed for dead torrent\n(4) We seed all torrent at 1Gbps\n\n~~~~~~~~~~~~~~~~~~~~~~~~~~~~~~~~~~~~~~~~~~~~~~~~~~~~~~~~~~~~~~~~~~~~~~~~~~~~~~~","torrent":{"xt":"urn:btih:76c9612fead012a815087c0ab36c6fd2ff597ec2","amp;dn":"Ayami.Shunka.ABS-155.Jav.Censored.DVDRip.XviD-MotTto","amp;tr":["udp%3A%2F%2Ftracker.openbittorrent.com%3A80","udp%3A%2F%2Fopen.demonii.com%3A1337","udp%3A%2F%2Ftracker.coppersurfer.tk%3A6969","udp%3A%2F%2Fexodus.desync.com%3A6969"],"infoHash":"76c9612fead012a815087c0ab36c6fd2ff597ec2","infoHashBuffer":{"type":"Buffer","data":[118,201,97,47,234,208,18,168,21,8,124,10,179,108,111,210,255,89,126,194]},"announce":[],"urlList":[]}}