{"title":"Complete ROM collection for RISC OS - Arthur to NCOS to Select","uid":5463078,"size":51347961,"categoryP":"applications","categoryS":"other_os","magnet":"?xt=urn:btih:949423a643c50a6bfbe55cdc62f66fcb6fc75900&amp;dn=Complete+ROM+collection+for+RISC+OS+-+Arthur+to+NCOS+to+Select&amp;tr=udp%3A%2F%2Ftracker.openbittorrent.com%3A80&amp;tr=udp%3A%2F%2Fopen.demonii.com%3A1337&amp;tr=udp%3A%2F%2Ftracker.coppersurfer.tk%3A6969&amp;tr=udp%3A%2F%2Fexodus.desync.com%3A6969","seeders":2,"leechers":0,"uploader":"antiques","files":2,"time":1269532308,"description":"        +----------------------------------------------------------------------+\n        |                                                                      |\n        |   Supplied......:  Acorn Antiques    Release name..:  ROMS_V1.rar    |\n        |   Packaged......:  filth             Release type..:  Util           |\n        |   Protection....:  none              Language......:  English        |\n        |   Crack/SN......:  n/a               Size..........:  48.9 MB        |\n        |   Format........:  ROM inside RAR    OS............:  RISC OS        |\n        |                                                                      |\n        |   MD5 checksum.................: c3613d8623874223cb02765c2db10317    |\n        |                                                                      |\n        |   ================================================================   |\n        |                            Description                               |\n        |   ================================================================   |\n        |                                                                      |\n        |   The ultimate collection of ROM images for RISC OS!                 |\n        |                                                                      |\n        |   Pretty much every version of RISC OS from 1987 to 2009, in a       |\n        |   format suitable for emulation. Please note that these are legacy   |\n        |   ROMs; check out our other releases for a full version of Select    |\n        |   including all disc applications (SELECT5i2.rar) and more still to  |\n        |   come!                                                              |\n        |                                                                      |\n        |   ================================================================   |\n        |   Special notice: Select 6i branch coming soon from Acorn Antiques!  |\n        |   ================================================================   |\n        |                                                                      |\n        |   This set contains the following ROM images, in three categories    |\n        |   (please see the included readme.txt in each folder for more        |\n        |   detailed contents descriptions):                                   |\n        |                                                                      |\n        |   1. Major = all mainstream RISC OS builds                           |\n        |      readme.txt                                                      |\n        |      ROM030                                                          |\n        |      ROM120                                                          |\n        |      ROM200                                                          |\n        |      ROM201                                                          |\n        |      ROM310                                                          |\n        |      ROM311                                                          |\n        |      ROM350                                                          |\n        |      ROM360                                                          |\n        |      ROM370                                                          |\n        |      ROM371                                                          |\n        |      ROM402                                                          |\n        |      ROM429.Select1i9                                                |\n        |      ROM433.Select2i3                                                |\n        |      ROM439.Select3i4                                                |\n        |      ROM610.Select4i4                                                |\n        |      ROM616.Select5i2                                                |\n        |                                                                      |\n        |   2. NCOS = all NCOS (Set-top box) builds                            |\n        |      readme.txt                                                      |\n        |      NCOS010                                                         |\n        |      NCOS106                                                         |\n        |      NCOS111                                                         |\n        |      NCOS513                                                         |\n        |      ROM361                                                          |\n        |      ROM361.ExtnRom                                                  |\n        |                                                                      |\n        |   3. Uncommon = older, unusual, or Select variant builds             |\n        |      readme.txt                                                      |\n        |      ROM200.A500Build                                                |\n        |      ROM200.UnknownVariant                                           |\n        |      ROM300                                                          |\n        |      ROM319                                                          |\n        |      ROM380.ARM6ARM7                                                 |\n        |      ROM380.SA                                                       |\n        |      ROM400.Pace1                                                    |\n        |      ROM400.Pace2                                                    |\n        |      ROM404                                                          |\n        |      ROM437.Select3i2                                                |\n        |      ROM437.Select3i3                                                |\n        |      ROM606.Select4i2                                                |\n        |      ROM610.Select4i4na                                              |\n        |      ROM614.Select5i1                                                |\n        |      ROM614.Select5i1na                                              |\n        |      ROM616.Select5i2na                                              |\n        |                                                                      |\n        +----------------------------------------------------------------------+\n        |                                                                      |\n        |   Visit our profile for more, including some vary rare releases!     |\n        |                                                                      |\n        |               &lt;a href=&quot; http://thepiratebay.se/user/antiques&quot; rel=&quot;nofollow&quot; target=&quot;_NEW&quot;&gt; http://thepiratebay.se/user/antiques&lt;/a&gt;                 |\n        |                                                                      |\n        |  [tags: risc, risc os, acorn, acorn user, riscos, magazine, cover]   |\n        |                                                                      |\n        +----------------------------------------------------------------------+\n        |                                                                      |\n        |   Please seed - this is for the benefit of the RISC OS community,    |\n        |   to ensure that these CDs and the files on them are never lost.     |\n        |   Do your part to help, but please do support legitimate developers! |\n        |                                                                      |\n        +----------------------------------------------------------------------+\n        |                                                                      |\n        |                  &lt;a class=&quot;__cf_email__&quot; href=&quot;/cdn-cgi/l/email-protection&quot; data-cfemail=&quot;49282a263b276728273d20383c2c3a673e283b2c33092e24282025672a2624&quot;&gt;[email&amp;#160;protected]&lt;/a&gt;&lt;script cf-hash='f9e31' type=&quot;text/javascript&quot;&gt;\n/* &lt;![CDATA[ */!function(){try{var t=&quot;currentScript&quot;in document?document.currentScript:function(){for(var t=document.getElementsByTagName(&quot;script&quot;),e=t.length;e--;)if(t[e].getAttribute(&quot;cf-hash&quot;))return t[e]}();if(t&amp;&amp;t.previousSibling){var e,r,n,i,c=t.previousSibling,a=c.getAttribute(&quot;data-cfemail&quot;);if(a){for(e=&quot;&quot;,r=parseInt(a.substr(0,2),16),n=2;a.length-n;n+=2)i=parseInt(a.substr(n,2),16)^r,e+=String.fromCharCode(i);e=document.createTextNode(e),c.parentNode.replaceChild(e,c)}}}catch(u){}}();/* ]]&gt; */&lt;/script&gt;                      |\n        |                                                                      |\n        &lt;a class=&quot;__cf_email__&quot; href=&quot;/cdn-cgi/l/email-protection&quot; data-cfemail=&quot;8da6a0a0a0a0a0a0a0a0a0a0a0a0a0a0a0a0a0a0a0a0a0a0a0a0a0a0a0a0a0a0a0a0a0a0a0a0a0a0a0a0a0a0a0a0a0a0a0a0a0a0a0a0a0a0a0a0a0a0a0a0a0a0a0a0&quot;&gt;[email&amp;#160;protected]&lt;/a&gt;&lt;script cf-hash='f9e31' type=&quot;text/javascript&quot;&gt;\n/* &lt;![CDATA[ */!function(){try{var t=&quot;currentScript&quot;in document?document.currentScript:function(){for(var t=document.getElementsByTagName(&quot;script&quot;),e=t.length;e--;)if(t[e].getAttribute(&quot;cf-hash&quot;))return t[e]}();if(t&amp;&amp;t.previousSibling){var e,r,n,i,c=t.previousSibling,a=c.getAttribute(&quot;data-cfemail&quot;);if(a){for(e=&quot;&quot;,r=parseInt(a.substr(0,2),16),n=2;a.length-n;n+=2)i=parseInt(a.substr(n,2),16)^r,e+=String.fromCharCode(i);e=document.createTextNode(e),c.parentNode.replaceChild(e,c)}}}catch(u){}}();/* ]]&gt; */&lt;/script&gt;------+\n        |                                                                      |\n        |                             Greetz to:                               |\n        |         flibble, acp, [qUE], Adny, teh Hodge, beardy Dave,           |\n        |         beardy John, Paul 'the man' and pig-fucker Johnson           |\n        |                                                                      |\n        |          And special greetz to our friends at RISCOSROMS:            |\n        |                                       |\n        |                                                                      |\n        +----------------------------------------------------------------------+\n                                                             ","torrent":{"xt":"urn:btih:949423a643c50a6bfbe55cdc62f66fcb6fc75900","amp;dn":"Complete+ROM+collection+for+RISC+OS+-+Arthur+to+NCOS+to+Select","amp;tr":["udp%3A%2F%2Ftracker.openbittorrent.com%3A80","udp%3A%2F%2Fopen.demonii.com%3A1337","udp%3A%2F%2Ftracker.coppersurfer.tk%3A6969","udp%3A%2F%2Fexodus.desync.com%3A6969"],"infoHash":"949423a643c50a6bfbe55cdc62f66fcb6fc75900","infoHashBuffer":{"type":"Buffer","data":[148,148,35,166,67,197,10,107,251,229,92,220,98,246,111,203,111,199,89,0]},"announce":[],"urlList":[]}}