{"title":"[FSX/P3D/P3D2]FS Real Time - 3D Softworks Design Studios v1.90 e","uid":9545243,"size":201706,"categoryP":"games","categoryS":"pc","magnet":"?xt=urn:btih:9eafdf556f6fae2cdb0c7110a0934d216f861ec2&amp;dn=%5BFSX%2FP3D%2FP3D2%5DFS+Real+Time+-+3D+Softworks+Design+Studios+v1.90+e&amp;tr=udp%3A%2F%2Ftracker.openbittorrent.com%3A80&amp;tr=udp%3A%2F%2Fopen.demonii.com%3A1337&amp;tr=udp%3A%2F%2Ftracker.coppersurfer.tk%3A6969&amp;tr=udp%3A%2F%2Fexodus.desync.com%3A6969","seeders":2,"leechers":0,"uploader":"einherz","files":1,"time":1391120425,"description":"all info in readme","torrent":{"xt":"urn:btih:9eafdf556f6fae2cdb0c7110a0934d216f861ec2","amp;dn":"%5BFSX%2FP3D%2FP3D2%5DFS+Real+Time+-+3D+Softworks+Design+Studios+v1.90+e","amp;tr":["udp%3A%2F%2Ftracker.openbittorrent.com%3A80","udp%3A%2F%2Fopen.demonii.com%3A1337","udp%3A%2F%2Ftracker.coppersurfer.tk%3A6969","udp%3A%2F%2Fexodus.desync.com%3A6969"],"infoHash":"9eafdf556f6fae2cdb0c7110a0934d216f861ec2","infoHashBuffer":{"type":"Buffer","data":[158,175,223,85,111,111,174,44,219,12,113,16,160,147,77,33,111,134,30,194]},"announce":[],"urlList":[]}}