{"title":"The.Big.Bang.Theory.S04E22.SWESUB.Nutc.divx","uid":6750782,"size":244681020,"categoryP":"video","categoryS":"tv_shows","magnet":"?xt=urn:btih:a88d8bd9c730b040603f5b4f67764572d235921f&amp;dn=The.Big.Bang.Theory.S04E22.SWESUB.Nutc.divx&amp;tr=udp%3A%2F%2Ftracker.openbittorrent.com%3A80&amp;tr=udp%3A%2F%2Fopen.demonii.com%3A1337&amp;tr=udp%3A%2F%2Ftracker.coppersurfer.tk%3A6969&amp;tr=udp%3A%2F%2Fexodus.desync.com%3A6969","seeders":2,"leechers":0,"uploader":"Nutcracker","files":1,"time":1318867128,"description":"SÃƒÂ¤song 4 avsnitt 22 med svensk text, taget frÃƒÂ¥n Kanal 5.\n\nSeedar ett antal dagar med taskig lina. Se till att seeda efter er.","torrent":{"xt":"urn:btih:a88d8bd9c730b040603f5b4f67764572d235921f","amp;dn":"The.Big.Bang.Theory.S04E22.SWESUB.Nutc.divx","amp;tr":["udp%3A%2F%2Ftracker.openbittorrent.com%3A80","udp%3A%2F%2Fopen.demonii.com%3A1337","udp%3A%2F%2Ftracker.coppersurfer.tk%3A6969","udp%3A%2F%2Fexodus.desync.com%3A6969"],"infoHash":"a88d8bd9c730b040603f5b4f67764572d235921f","infoHashBuffer":{"type":"Buffer","data":[168,141,139,217,199,48,176,64,96,63,91,79,103,118,69,114,210,53,146,31]},"announce":[],"urlList":[]}}