{"title":"The.League.S05E05.1080p.WEB-DL.DD5.1.h.264-pcsyndicate [PublicHD","uid":8996386,"size":857469826,"categoryP":"video","categoryS":"hd___tv_shows","magnet":"?xt=urn:btih:a9d4e21ab491dc2715a03612ececef19e6acc120&amp;dn=The.League.S05E05.1080p.WEB-DL.DD5.1.h.264-pcsyndicate+%5BPublicHD&amp;tr=udp%3A%2F%2Ftracker.openbittorrent.com%3A80&amp;tr=udp%3A%2F%2Fopen.demonii.com%3A1337&amp;tr=udp%3A%2F%2Ftracker.coppersurfer.tk%3A6969&amp;tr=udp%3A%2F%2Fexodus.desync.com%3A6969","seeders":2,"leechers":4,"uploader":"DibyaTPB","files":2,"time":1380872070,"description":"\n                PublicHD - High-Definition Bittorrent Community\n      \n                               \n              ----------------------------------------------------\n\nThe.League.S05E05.1080p.WEB-DL.DD5.1.h.264-pcsyndicate [PublicHD]\n \nLength..............: 21mn 20s\nVideo...............: H264 @ 5355Kbps (1912x1072)\nFPS.................: 23.976 FPS\nAudio...............: AC3","torrent":{"xt":"urn:btih:a9d4e21ab491dc2715a03612ececef19e6acc120","amp;dn":"The.League.S05E05.1080p.WEB-DL.DD5.1.h.264-pcsyndicate+%5BPublicHD","amp;tr":["udp%3A%2F%2Ftracker.openbittorrent.com%3A80","udp%3A%2F%2Fopen.demonii.com%3A1337","udp%3A%2F%2Ftracker.coppersurfer.tk%3A6969","udp%3A%2F%2Fexodus.desync.com%3A6969"],"infoHash":"a9d4e21ab491dc2715a03612ececef19e6acc120","infoHashBuffer":{"type":"Buffer","data":[169,212,226,26,180,145,220,39,21,160,54,18,236,236,239,25,230,172,193,32]},"announce":[],"urlList":[]}}