{"title":"Ska-p - Lagrimas y Gozos [2008]","uid":4431406,"size":75048845,"categoryP":"audio","categoryS":"music","magnet":"?xt=urn:btih:d7a163fd82ff68c852863eacf049cc5766afea79&amp;dn=Ska-p+-+Lagrimas+y+Gozos+%5B2008%5D&amp;tr=udp%3A%2F%2Ftracker.openbittorrent.com%3A80&amp;tr=udp%3A%2F%2Fopen.demonii.com%3A1337&amp;tr=udp%3A%2F%2Ftracker.coppersurfer.tk%3A6969&amp;tr=udp%3A%2F%2Fexodus.desync.com%3A6969","seeders":2,"leechers":0,"uploader":"Mois20","files":14,"time":1223310819,"description":"Ska-p - Lagrimas y Gozos [2008]","torrent":{"xt":"urn:btih:d7a163fd82ff68c852863eacf049cc5766afea79","amp;dn":"Ska-p+-+Lagrimas+y+Gozos+%5B2008%5D","amp;tr":["udp%3A%2F%2Ftracker.openbittorrent.com%3A80","udp%3A%2F%2Fopen.demonii.com%3A1337","udp%3A%2F%2Ftracker.coppersurfer.tk%3A6969","udp%3A%2F%2Fexodus.desync.com%3A6969"],"infoHash":"d7a163fd82ff68c852863eacf049cc5766afea79","infoHashBuffer":{"type":"Buffer","data":[215,161,99,253,130,255,104,200,82,134,62,172,240,73,204,87,102,175,234,121]},"announce":[],"urlList":[]}}