{"title":"Girlfriends Season 2 [gsum]","uid":6822702,"size":4463701551,"categoryP":"video","categoryS":"tv_shows","magnet":"?xt=urn:btih:f721faec6b149e2664b6ec635589c5bc80ede185&amp;dn=Girlfriends+Season+2+%5Bgsum%5D&amp;tr=udp%3A%2F%2Ftracker.openbittorrent.com%3A80&amp;tr=udp%3A%2F%2Fopen.demonii.com%3A1337&amp;tr=udp%3A%2F%2Ftracker.coppersurfer.tk%3A6969&amp;tr=udp%3A%2F%2Fexodus.desync.com%3A6969","seeders":2,"leechers":2,"uploader":"mystic_alinutza","files":26,"time":1321458561,"description":"A look at the lives, loves, and losses of four different women, Toni, Maya, Lynn, and Joan. ","torrent":{"xt":"urn:btih:f721faec6b149e2664b6ec635589c5bc80ede185","amp;dn":"Girlfriends+Season+2+%5Bgsum%5D","amp;tr":["udp%3A%2F%2Ftracker.openbittorrent.com%3A80","udp%3A%2F%2Fopen.demonii.com%3A1337","udp%3A%2F%2Ftracker.coppersurfer.tk%3A6969","udp%3A%2F%2Fexodus.desync.com%3A6969"],"infoHash":"f721faec6b149e2664b6ec635589c5bc80ede185","infoHashBuffer":{"type":"Buffer","data":[247,33,250,236,107,20,158,38,100,182,236,99,85,137,197,188,128,237,225,133]},"announce":[],"urlList":[]}}